disc_python/__init__.py
disc_python/disc.py
disc_python/algoritmos/__init__.py
disc_python/algoritmos/aproximacion.py
disc_python/algoritmos/determistas.py
disc_python/algoritmos/generic.py
disc_python/algoritmos/paralelos.py
disc_python/corpus/__init__.py
disc_python/corpus/wornet.py
disc_python-1.0.1.dist-info/LICENSE
disc_python-1.0.1.dist-info/METADATA
disc_python-1.0.1.dist-info/WHEEL
disc_python-1.0.1.dist-info/top_level.txt
disc_python-1.0.1.dist-info/RECORD
