Metadata-Version: 2.1
Name: disc-python
Version: 1.0.1
Summary: Library to compute conceptual distance by using DIS-C method
Home-page: https://gitlab.com/TebanMT
Author: Esteban Mendiola Tellez
Author-email: mendiola_esteban@outlook.com
License: MIT
License-File: LICENSE
Requires-Dist: networkx
Requires-Dist: numpy
Requires-Dist: nltk
